altdg/__init__.py
altdg/api.py
altdg-1.0.5.dist-info/METADATA
altdg-1.0.5.dist-info/WHEEL
altdg-1.0.5.dist-info/entry_points.txt
altdg-1.0.5.dist-info/top_level.txt
altdg-1.0.5.dist-info/RECORD
