Metadata-Version: 2.1
Name: altdg
Version: 1.0.5
Summary: Utility libraries from Alternative Data Group
Home-page: https://github.com/altdg/bulk_mapper
License: MIT
Keywords: adg alternative data group
Platform: UNKNOWN
Classifier: Environment :: Web Environment
Classifier: Intended Audience :: Developers
Classifier: License :: OSI Approved :: MIT License
Classifier: Operating System :: OS Independent
Classifier: Programming Language :: Python
Classifier: Programming Language :: Python :: 3.6
Classifier: Topic :: Internet :: WWW/HTTP
Requires-Python: >=3.6
Requires-Dist: requests
Requires-Dist: chardet
